nivacloud_logging/__init__.py
nivacloud_logging/aiohttp_trace.py
nivacloud_logging/flask_trace.py
nivacloud_logging/gunicorn_logger.py
nivacloud_logging/json_formatter.py
nivacloud_logging/log_utils.py
nivacloud_logging/requests_trace.py
nivacloud_logging/starlette_trace.py
nivacloud_logging-1.0.0.dist-info/LICENSE
nivacloud_logging-1.0.0.dist-info/METADATA
nivacloud_logging-1.0.0.dist-info/WHEEL
nivacloud_logging-1.0.0.dist-info/top_level.txt
nivacloud_logging-1.0.0.dist-info/RECORD
